captchabreaker/__init__.py
captchabreaker/_version.py
captchabreaker/breaker.py
captchabreaker/tokenizer.py
captchabreaker-0.1.1.dist-info/METADATA
captchabreaker-0.1.1.dist-info/WHEEL
captchabreaker-0.1.1.dist-info/RECORD
