Metadata-Version: 2.4
Name: captchabreaker
Version: 0.1.1
Summary: A library to break captchas using ONNX models.
Project-URL: homepage, https://github.com/ramSeraph/captchabreaker
Project-URL: repository, https://github.com/ramSeraph/captchabreaker.git
Author-email: Sreeram Kandimalla <kandimalla.sreeram@gmail.com>
Requires-Python: >=3.9
Requires-Dist: onnx
Requires-Dist: onnxruntime
Requires-Dist: pillow
Requires-Dist: torch
Requires-Dist: torchvision
